paraminjector/TODO.md
paraminjector/__init__.py
paraminjector/_injector.py
paraminjector/annotations.py
paraminjector/dynamic.py
paraminjector/exceptions.py
paraminjector/static.py
paraminjector/typed_callable.py
paraminjector-0.1.1.dist-info/WHEEL
paraminjector-0.1.1.dist-info/METADATA
paraminjector-0.1.1.dist-info/RECORD
